MANIFEST.in
README.rst
setup.py
drf_eventlog/__init__.py
drf_eventlog/logger.py
drf_eventlog/models.py
drf_eventlog/routers.py
drf_eventlog/serializers.py
drf_eventlog/signals.py
drf_eventlog/urls.py
drf_eventlog/views.py
drf_eventlog.egg-info/PKG-INFO
drf_eventlog.egg-info/SOURCES.txt
drf_eventlog.egg-info/dependency_links.txt
drf_eventlog.egg-info/not-zip-safe
drf_eventlog.egg-info/requires.txt
drf_eventlog.egg-info/top_level.txt
drf_eventlog/migrations/0001_initial.py
drf_eventlog/migrations/__init__.py
drf_eventlog/tests/__init__.py
drf_eventlog/tests/authentication.py
drf_eventlog/tests/models.py
drf_eventlog/tests/serializers.py
drf_eventlog/tests/tests.py
drf_eventlog/tests/urls.py