Metadata-Version: 1.1
Name: drf-eventlog
Version: 0.0.3
Summary: Log events in your app and get REST APIs with filtering for them.
Home-page: http://subramaniank.github.io
Author: K Subramanian
Author-email: baathai@gmail.com
License: UNKNOWN
Platform: UNKNOWN
Classifier: Environment :: Web Environment
Classifier: Framework :: Django
Classifier: Intended Audience :: Developers
Classifier: License :: OSI Approved :: BSD License
Classifier: Operating System :: OS Independent
Classifier: Programming Language :: Python
Classifier: Programming Language :: Python :: 3
Classifier: Topic :: Internet :: WWW/HTTP
